examples/__init__.py
examples/langchain/README.md
examples/langchain/__init__.py
examples/langchain/basic_agent.py
examples/langchain/customer_support.py
examples/langchain/personal_assistant.py
examples/langchain/sql_agent.py
examples/langgraph/__init__.py
examples/langgraph/langgraph_rag.py
examples/langgraph/langgraph_sql_agent.py
examples/openai/__init__.py
examples/openai/openai_rag.py
examples/openai_agents_sdk/README.md
examples/openai_agents_sdk/__init__.py
examples/openai_agents_sdk/customer_service.py
examples/openai_agents_sdk/financial_research_agent.py
examples/openai_agents_sdk/llm_as_a_judge.py
examples/openai_agents_sdk/routing.py
examples/pydantic_ai/.env.example
examples/pydantic_ai/README.md
examples/pydantic_ai/__init__.py
examples/pydantic_ai/bank_support.py
examples/pydantic_ai/flight_booking.py
examples/pydantic_ai/question_graph.py
examples/pydantic_ai/sql_gen.py
examples/pydantic_ai/structured_output.py
examples/quickstart/__init__.py
examples/quickstart/chatbot.py
examples/quickstart/problem_solver.py
examples/quickstart/sleepy_poet.py
examples/quickstart/weather_agent.py
examples/sql_utils.py
pixie_examples-0.2.9.dist-info/METADATA
pixie_examples-0.2.9.dist-info/WHEEL
pixie_examples-0.2.9.dist-info/licenses/LICENSE
pixie_examples-0.2.9.dist-info/RECORD
