Metadata-Version: 2.4
Name: pixie-examples
Version: 0.2.9
Summary: examples for using Pixie
License: MIT
License-File: LICENSE
Author: Yiou Li
Author-email: yol@gopixie.ai
Requires-Python: >=3.11,<3.14
Classifier: License :: OSI Approved :: MIT License
Classifier: Programming Language :: Python :: 3
Classifier: Programming Language :: Python :: 3.11
Classifier: Programming Language :: Python :: 3.12
Classifier: Programming Language :: Python :: 3.13
Requires-Dist: beautifulsoup4 (>=4.14.3,<5.0.0)
Requires-Dist: langchain (>=1.2.3,<2.0.0)
Requires-Dist: langchain-openai (>=1.1.7,<2.0.0)
Requires-Dist: langchain-text-splitters (>=1.1.0,<2.0.0)
Requires-Dist: langgraph (>=1.0.5,<2.0.0)
Requires-Dist: lxml (>=6.0.2,<7.0.0)
Requires-Dist: numpy (>=2.4.1,<3.0.0)
Requires-Dist: openai-agents (>=0.6.5,<0.7.0)
Requires-Dist: openinference-instrumentation-crewai (>=0.1.17,<0.2.0)
Requires-Dist: openinference-instrumentation-dspy (>=0.1.33,<0.2.0)
Requires-Dist: openinference-instrumentation-google-adk (>=0.1.8,<0.2.0)
Requires-Dist: openinference-instrumentation-openai-agents (>=1.4.0,<2.0.0)
Requires-Dist: pixie-sdk (==0.2.9)
Requires-Dist: pydantic (>=2.7.4,<3.0.0)
Requires-Dist: pydantic-ai-slim (>=1.39.0,<2.0.0)
Requires-Dist: pymarkdownlnt (>=0.9.34,<0.10.0)
Requires-Dist: requests (>=2.32.5,<3.0.0)
Requires-Dist: sqlalchemy (>=2.0.45,<3.0.0)
Project-URL: Changelog, https://github.com/yiouli/pixie-examples/commits/main/
Project-URL: Documentation, https://yiouli.github.io/pixie-sdk-py/
Project-URL: Homepage, https://gopixie.ai/?url=https%3A%2F%2Fdemo.yiouli.us%2Fgraphql
Project-URL: Issues, https://github.com/yiouli/pixie-examples/issues
Project-URL: Repository, https://github.com/yiouli/pixie-examples
